xverif/__init__.py
xverif/xverif.py
xverif-0.1.0.dist-info/LICENSE
xverif-0.1.0.dist-info/METADATA
xverif-0.1.0.dist-info/WHEEL
xverif-0.1.0.dist-info/RECORD
