Metadata-Version: 2.1
Name: xverif
Version: 0.1.0
Summary: Xarray-based package for forecasts/simulations verification
Author: Gionata Ghiggi,
Author-email: gionata.ghiggi@epfl.ch
Requires-Python: >=3.9,<4.0
Classifier: Programming Language :: Python :: 3
Classifier: Programming Language :: Python :: 3.9
Classifier: Programming Language :: Python :: 3.10
Classifier: Programming Language :: Python :: 3.11
Requires-Dist: dask[distributed] (>=2023.4.1,<2024.0.0)
Requires-Dist: flox (>=0.7.1,<0.8.0)
Requires-Dist: numba (>=0.57.0,<0.58.0)
Requires-Dist: rechunker (>=0.5.1,<0.6.0)
Requires-Dist: xarray (>=2023.4.2,<2024.0.0)
